{"id":"bill_of_materials:13a3da4e-1a0c-5ed9-adb8-c97c97be8f01","subject":{"__typename":"Package","id":"package_types:golang","type":"golang","namespaces":[{"id":"package_namespaces:golangguac-split-@@github.com/duosecurity","namespace":"github.com/duosecurity","names":[{"id":"package_names:0e6723d4-8700-5126-a678-15e25db85d60","name":"duo_api_golang","versions":[{"id":"package_versions:4ea0ffe5-0ead-5a45-8dc7-bf6fb57e902b","purl":"pkg:golang/github.com/duosecurity/duo_api_golang@v0.0.0-20190308151101-6c680f768e74","version":"v0.0.0-20190308151101-6c680f768e74","qualifiers":[],"subpath":""}]}]}]},"uri":"pkg:golang/github.com/duosecurity/duo_api_golang@v0.0.0-20190308151101-6c680f768e74","algorithm":"sha256","digest":"9d9e786f1b4888081d4731f10c8b0b12c6ac17b8bb537d055d3afa2cb45b32ff","downloadLocation":"deps.dev","origin":"deps.dev","collector":"deps.dev","knownSince":"2024-11-25T15:59:06.512669Z","documentRef":"sha256_9d9e786f1b4888081d4731f10c8b0b12c6ac17b8bb537d055d3afa2cb45b32ff","includedSoftware":[{"__typename":"Package","id":"package_types:golang","type":"golang","namespaces":[{"id":"package_namespaces:golangguac-split-@@github.com/duosecurity","namespace":"github.com/duosecurity","names":[{"id":"package_names:0e6723d4-8700-5126-a678-15e25db85d60","name":"duo_api_golang","versions":[{"id":"package_versions:4ea0ffe5-0ead-5a45-8dc7-bf6fb57e902b","purl":"pkg:golang/github.com/duosecurity/duo_api_golang@v0.0.0-20190308151101-6c680f768e74","version":"v0.0.0-20190308151101-6c680f768e74","qualifiers":[],"subpath":""}]}]}]}],"includedDependencies":[],"includedOccurrences":[]}