{"id":"bill_of_materials:59022f1d-cc22-52d9-82e4-134e1a9ee493","subject":{"__typename":"Package","id":"package_types:golang","type":"golang","namespaces":[{"id":"package_namespaces:golangguac-split-@@github.com/go-logr","namespace":"github.com/go-logr","names":[{"id":"package_names:273dc3a4-e4df-5e5d-a3e8-e7f35547cd8f","name":"logr","versions":[{"id":"package_versions:ac597003-34cf-5a43-a0b8-d625cf198d5f","purl":"pkg:golang/github.com/go-logr/logr@v1.2.0","version":"v1.2.0","qualifiers":[],"subpath":""}]}]}]},"uri":"pkg:golang/github.com/go-logr/logr@v1.2.0","algorithm":"sha256","digest":"772c701efd79b059060b920785d87678b57b9b23b38797fb95869878b18ec206","downloadLocation":"deps.dev","origin":"deps.dev","collector":"deps.dev","knownSince":"2024-11-25T15:59:06.594227Z","documentRef":"sha256_772c701efd79b059060b920785d87678b57b9b23b38797fb95869878b18ec206","includedSoftware":[{"__typename":"Package","id":"package_types:golang","type":"golang","namespaces":[{"id":"package_namespaces:golangguac-split-@@github.com/go-logr","namespace":"github.com/go-logr","names":[{"id":"package_names:273dc3a4-e4df-5e5d-a3e8-e7f35547cd8f","name":"logr","versions":[{"id":"package_versions:ac597003-34cf-5a43-a0b8-d625cf198d5f","purl":"pkg:golang/github.com/go-logr/logr@v1.2.0","version":"v1.2.0","qualifiers":[],"subpath":""}]}]}]}],"includedDependencies":[],"includedOccurrences":[]}