{"id":"bill_of_materials:145bf277-ddc6-56e0-9c56-a8cd7261a58d","subject":{"__typename":"Package","id":"package_types:golang","type":"golang","namespaces":[{"id":"package_namespaces:golangguac-split-@@cloud.google.com","namespace":"cloud.google.com","names":[{"id":"package_names:0c47e8bd-f53b-556f-8794-11506c98d268","name":"go","versions":[{"id":"package_versions:6c9a5bc9-097f-55ab-a7b0-937f2be892c2","purl":"pkg:golang/cloud.google.com/go@v0.97.0","version":"v0.97.0","qualifiers":[],"subpath":""}]}]}]},"uri":"pkg:golang/cloud.google.com/go@v0.97.0","algorithm":"sha256","digest":"688406ad4a6f7514bc9d26391df8a8d34b322dd2a3ba59e763bffe5fcc6b6f7d","downloadLocation":"deps.dev","origin":"deps.dev","collector":"deps.dev","knownSince":"2024-11-25T15:36:26.086314Z","documentRef":"sha256_688406ad4a6f7514bc9d26391df8a8d34b322dd2a3ba59e763bffe5fcc6b6f7d","includedSoftware":[{"__typename":"Package","id":"package_types:golang","type":"golang","namespaces":[{"id":"package_namespaces:golangguac-split-@@github.com/golang","namespace":"github.com/golang","names":[{"id":"package_names:320a482a-3ad7-5a14-ad48-9304da558d41","name":"protobuf","versions":[{"id":"package_versions:59ba7431-d04d-5b33-b4be-ef0b31a54b94","purl":"pkg:golang/github.com/golang/protobuf@v1.5.2","version":"v1.5.2","qualifiers":[],"subpath":""}]}]}]},{"__typename":"Package","id":"package_types:golang","type":"golang","namespaces":[{"id":"package_namespaces:golangguac-split-@@github.com/golang","namespace":"github.com/golang","names":[{"id":"package_names:4cfb47fa-723f-535e-a84f-7ea9670c1b1b","name":"groupcache","versions":[{"id":"package_versions:50b2a3e6-916a-5079-a9ab-a46ef67a0cf9","purl":"pkg:golang/github.com/golang/groupcache@v0.0.0-20200121045136-8c9f03a8e57e","version":"v0.0.0-20200121045136-8c9f03a8e57e","qualifiers":[],"subpath":""}]}]}]},{"__typename":"Package","id":"package_types:golang","type":"golang","namespaces":[{"id":"package_namespaces:golangguac-split-@@google.golang.org","namespace":"google.golang.org","names":[{"id":"package_names:4833fe40-e306-5891-a53c-dda7e8f6d5fc","name":"protobuf","versions":[{"id":"package_versions:be59d0a9-9c01-5106-82f2-216581252279","purl":"pkg:golang/google.golang.org/protobuf@v1.27.1","version":"v1.27.1","qualifiers":[],"subpath":""}]}]}]},{"__typename":"Package","id":"package_types:golang","type":"golang","namespaces":[{"id":"package_namespaces:golangguac-split-@@golang.org/x","namespace":"golang.org/x","names":[{"id":"package_names:dc25e99a-787e-5afb-9222-fa36a50e3b01","name":"text","versions":[{"id":"package_versions:e4b70ee4-4510-5052-8060-90dc4be40754","purl":"pkg:golang/golang.org/x/text@v0.3.6","version":"v0.3.6","qualifiers":[],"subpath":""}]}]}]},{"__typename":"Package","id":"package_types:golang","type":"golang","namespaces":[{"id":"package_namespaces:golangguac-split-@@golang.org/x","namespace":"golang.org/x","names":[{"id":"package_names:1c7c772b-8d57-5337-a23e-5180e6144a9a","name":"oauth2","versions":[{"id":"package_versions:1e573995-657f-55f1-86e8-cbd0c69cd52c","purl":"pkg:golang/golang.org/x/oauth2@v0.0.0-20210819190943-2bc19b11175f","version":"v0.0.0-20210819190943-2bc19b11175f","qualifiers":[],"subpath":""}]}]}]},{"__typename":"Package","id":"package_types:golang","type":"golang","namespaces":[{"id":"package_namespaces:golangguac-split-@@cloud.google.com/go","namespace":"cloud.google.com/go","names":[{"id":"package_names:076437cc-3046-55f2-b2ac-e1cf018c5dbc","name":"storage","versions":[{"id":"package_versions:b8289d60-77da-52d7-a3c5-25f09a834c7b","purl":"pkg:golang/cloud.google.com/go/storage@v1.10.0","version":"v1.10.0","qualifiers":[],"subpath":""}]}]}]},{"__typename":"Package","id":"package_types:golang","type":"golang","namespaces":[{"id":"package_namespaces:golangguac-split-@@","namespace":"","names":[{"id":"package_names:b3b4b1d9-a334-5a3b-b636-88b080edba06","name":"go.opencensus.io","versions":[{"id":"package_versions:4c42e74c-4502-5f60-8974-c2f80fdf5eaf","purl":"pkg:golang/go.opencensus.io@v0.23.0","version":"v0.23.0","qualifiers":[],"subpath":""}]}]}]},{"__typename":"Package","id":"package_types:golang","type":"golang","namespaces":[{"id":"package_namespaces:golangguac-split-@@cloud.google.com","namespace":"cloud.google.com","names":[{"id":"package_names:0c47e8bd-f53b-556f-8794-11506c98d268","name":"go","versions":[{"id":"package_versions:6c9a5bc9-097f-55ab-a7b0-937f2be892c2","purl":"pkg:golang/cloud.google.com/go@v0.97.0","version":"v0.97.0","qualifiers":[],"subpath":""}]}]}]},{"__typename":"Package","id":"package_types:golang","type":"golang","namespaces":[{"id":"package_namespaces:golangguac-split-@@golang.org/x","namespace":"golang.org/x","names":[{"id":"package_names:f7730425-ecf7-55a4-84ea-62392d8d5749","name":"xerrors","versions":[{"id":"package_versions:ccbe0b17-a320-5b1c-9cf8-2453828468e1","purl":"pkg:golang/golang.org/x/xerrors@v0.0.0-20200804184101-5ec99f83aff1","version":"v0.0.0-20200804184101-5ec99f83aff1","qualifiers":[],"subpath":""}]}]}]},{"__typename":"Package","id":"package_types:golang","type":"golang","namespaces":[{"id":"package_namespaces:golangguac-split-@@github.com/google","namespace":"github.com/google","names":[{"id":"package_names:238c18ee-09d5-56bf-bc39-78997eb030f3","name":"go-cmp","versions":[{"id":"package_versions:79827ed9-63b5-5388-a107-aa05bedab549","purl":"pkg:golang/github.com/google/go-cmp@v0.5.6","version":"v0.5.6","qualifiers":[],"subpath":""}]}]}]},{"__typename":"Package","id":"package_types:golang","type":"golang","namespaces":[{"id":"package_namespaces:golangguac-split-@@google.golang.org","namespace":"google.golang.org","names":[{"id":"package_names:3f25aec7-5b95-5d8e-b51c-1046029359b2","name":"appengine","versions":[{"id":"package_versions:45b1d4fc-7f94-5973-9595-af0628662e22","purl":"pkg:golang/google.golang.org/appengine@v1.6.7","version":"v1.6.7","qualifiers":[],"subpath":""}]}]}]},{"__typename":"Package","id":"package_types:golang","type":"golang","namespaces":[{"id":"package_namespaces:golangguac-split-@@golang.org/x","namespace":"golang.org/x","names":[{"id":"package_names:10660366-cd81-5fa5-9ed3-5750e84e996e","name":"net","versions":[{"id":"package_versions:b0d4fdab-a6ad-5edc-8442-d8785917bcdd","purl":"pkg:golang/golang.org/x/net@v0.0.0-20210503060351-7fd8e65b6420","version":"v0.0.0-20210503060351-7fd8e65b6420","qualifiers":[],"subpath":""}]}]}]},{"__typename":"Package","id":"package_types:golang","type":"golang","namespaces":[{"id":"package_namespaces:golangguac-split-@@github.com/google/martian","namespace":"github.com/google/martian","names":[{"id":"package_names:a57a9626-1438-5d74-9321-bb5b15a6bb4b","name":"v3","versions":[{"id":"package_versions:205cc45a-f352-54fd-905d-b603026caecf","purl":"pkg:golang/github.com/google/martian/v3@v3.2.1","version":"v3.2.1","qualifiers":[],"subpath":""}]}]}]},{"__typename":"Package","id":"package_types:golang","type":"golang","namespaces":[{"id":"package_namespaces:golangguac-split-@@google.golang.org","namespace":"google.golang.org","names":[{"id":"package_names:c1c08a0f-8baa-539c-91ad-f5e143249f4b","name":"genproto","versions":[{"id":"package_versions:bb1b4307-9171-5960-8539-859ef923ade0","purl":"pkg:golang/google.golang.org/genproto@v0.0.0-20210924002016-3dee208752a0","version":"v0.0.0-20210924002016-3dee208752a0","qualifiers":[],"subpath":""}]}]}]},{"__typename":"Package","id":"package_types:golang","type":"golang","namespaces":[{"id":"package_namespaces:golangguac-split-@@google.golang.org","namespace":"google.golang.org","names":[{"id":"package_names:574d6a3b-6036-55d4-ae5b-f313de75887b","name":"api","versions":[{"id":"package_versions:f3694f55-063e-54c9-9d8b-cbb45f87f9ae","purl":"pkg:golang/google.golang.org/api@v0.57.0","version":"v0.57.0","qualifiers":[],"subpath":""}]}]}]},{"__typename":"Package","id":"package_types:golang","type":"golang","namespaces":[{"id":"package_namespaces:golangguac-split-@@github.com/googleapis/gax-go","namespace":"github.com/googleapis/gax-go","names":[{"id":"package_names:ea417608-e3b0-5bfb-9889-95b0f158d525","name":"v2","versions":[{"id":"package_versions:6b60d487-2838-5ec8-b723-ff640f11db54","purl":"pkg:golang/github.com/googleapis/gax-go/v2@v2.1.0","version":"v2.1.0","qualifiers":[],"subpath":""}]}]}]},{"__typename":"Package","id":"package_types:golang","type":"golang","namespaces":[{"id":"package_namespaces:golangguac-split-@@google.golang.org","namespace":"google.golang.org","names":[{"id":"package_names:2dc79dd0-c1ee-528a-a1a8-7c34d7d70cf4","name":"grpc","versions":[{"id":"package_versions:3532d212-49c1-5312-81e0-934288dbff6f","purl":"pkg:golang/google.golang.org/grpc@v1.40.0","version":"v1.40.0","qualifiers":[],"subpath":""}]}]}]},{"__typename":"Package","id":"package_types:golang","type":"golang","namespaces":[{"id":"package_namespaces:golangguac-split-@@golang.org/x","namespace":"golang.org/x","names":[{"id":"package_names:6c0a9691-7a6f-5176-a395-cab080877631","name":"sys","versions":[{"id":"package_versions:23e077f5-164f-5824-94be-59a13126e7d8","purl":"pkg:golang/golang.org/x/sys@v0.0.0-20210908233432-aa78b53d3365","version":"v0.0.0-20210908233432-aa78b53d3365","qualifiers":[],"subpath":""}]}]}]}],"includedDependencies":[{"id":"dependencies:8c6cd28a-e94f-5c35-94ba-0ab5b820b3b1","justification":"dependency data collected via deps.dev","package":{"id":"package_types:golang","type":"golang","namespaces":[{"id":"package_namespaces:golangguac-split-@@cloud.google.com","namespace":"cloud.google.com","names":[{"id":"package_names:0c47e8bd-f53b-556f-8794-11506c98d268","name":"go","versions":[{"id":"package_versions:6c9a5bc9-097f-55ab-a7b0-937f2be892c2","purl":"pkg:golang/cloud.google.com/go@v0.97.0","version":"v0.97.0","qualifiers":[],"subpath":""}]}]}]},"dependencyPackage":{"id":"package_types:golang","type":"golang","namespaces":[{"id":"package_namespaces:golangguac-split-@@cloud.google.com/go","namespace":"cloud.google.com/go","names":[{"id":"package_names:076437cc-3046-55f2-b2ac-e1cf018c5dbc","name":"storage","versions":[{"id":"package_versions:b8289d60-77da-52d7-a3c5-25f09a834c7b","purl":"pkg:golang/cloud.google.com/go/storage@v1.10.0","version":"v1.10.0","qualifiers":[],"subpath":""}]}]}]},"dependencyType":"DIRECT","origin":"deps.dev","collector":"deps.dev"},{"id":"dependencies:e475d105-c829-5f4f-bcf2-8eeb555968d7","justification":"dependency data collected via deps.dev","package":{"id":"package_types:golang","type":"golang","namespaces":[{"id":"package_namespaces:golangguac-split-@@cloud.google.com","namespace":"cloud.google.com","names":[{"id":"package_names:0c47e8bd-f53b-556f-8794-11506c98d268","name":"go","versions":[{"id":"package_versions:6c9a5bc9-097f-55ab-a7b0-937f2be892c2","purl":"pkg:golang/cloud.google.com/go@v0.97.0","version":"v0.97.0","qualifiers":[],"subpath":""}]}]}]},"dependencyPackage":{"id":"package_types:golang","type":"golang","namespaces":[{"id":"package_namespaces:golangguac-split-@@github.com/golang","namespace":"github.com/golang","names":[{"id":"package_names:320a482a-3ad7-5a14-ad48-9304da558d41","name":"protobuf","versions":[{"id":"package_versions:59ba7431-d04d-5b33-b4be-ef0b31a54b94","purl":"pkg:golang/github.com/golang/protobuf@v1.5.2","version":"v1.5.2","qualifiers":[],"subpath":""}]}]}]},"dependencyType":"DIRECT","origin":"deps.dev","collector":"deps.dev"},{"id":"dependencies:3b52780f-c08a-5033-9849-caa424c7f679","justification":"dependency data collected via deps.dev","package":{"id":"package_types:golang","type":"golang","namespaces":[{"id":"package_namespaces:golangguac-split-@@cloud.google.com","namespace":"cloud.google.com","names":[{"id":"package_names:0c47e8bd-f53b-556f-8794-11506c98d268","name":"go","versions":[{"id":"package_versions:6c9a5bc9-097f-55ab-a7b0-937f2be892c2","purl":"pkg:golang/cloud.google.com/go@v0.97.0","version":"v0.97.0","qualifiers":[],"subpath":""}]}]}]},"dependencyPackage":{"id":"package_types:golang","type":"golang","namespaces":[{"id":"package_namespaces:golangguac-split-@@github.com/google","namespace":"github.com/google","names":[{"id":"package_names:238c18ee-09d5-56bf-bc39-78997eb030f3","name":"go-cmp","versions":[{"id":"package_versions:79827ed9-63b5-5388-a107-aa05bedab549","purl":"pkg:golang/github.com/google/go-cmp@v0.5.6","version":"v0.5.6","qualifiers":[],"subpath":""}]}]}]},"dependencyType":"DIRECT","origin":"deps.dev","collector":"deps.dev"},{"id":"dependencies:78e96d1f-918e-50d1-b4de-e43582e41214","justification":"dependency data collected via deps.dev","package":{"id":"package_types:golang","type":"golang","namespaces":[{"id":"package_namespaces:golangguac-split-@@cloud.google.com","namespace":"cloud.google.com","names":[{"id":"package_names:0c47e8bd-f53b-556f-8794-11506c98d268","name":"go","versions":[{"id":"package_versions:6c9a5bc9-097f-55ab-a7b0-937f2be892c2","purl":"pkg:golang/cloud.google.com/go@v0.97.0","version":"v0.97.0","qualifiers":[],"subpath":""}]}]}]},"dependencyPackage":{"id":"package_types:golang","type":"golang","namespaces":[{"id":"package_namespaces:golangguac-split-@@github.com/google/martian","namespace":"github.com/google/martian","names":[{"id":"package_names:a57a9626-1438-5d74-9321-bb5b15a6bb4b","name":"v3","versions":[{"id":"package_versions:205cc45a-f352-54fd-905d-b603026caecf","purl":"pkg:golang/github.com/google/martian/v3@v3.2.1","version":"v3.2.1","qualifiers":[],"subpath":""}]}]}]},"dependencyType":"DIRECT","origin":"deps.dev","collector":"deps.dev"},{"id":"dependencies:3eedd763-fa7d-507e-a1c7-9d5a1ef14a21","justification":"dependency data collected via deps.dev","package":{"id":"package_types:golang","type":"golang","namespaces":[{"id":"package_namespaces:golangguac-split-@@cloud.google.com","namespace":"cloud.google.com","names":[{"id":"package_names:0c47e8bd-f53b-556f-8794-11506c98d268","name":"go","versions":[{"id":"package_versions:6c9a5bc9-097f-55ab-a7b0-937f2be892c2","purl":"pkg:golang/cloud.google.com/go@v0.97.0","version":"v0.97.0","qualifiers":[],"subpath":""}]}]}]},"dependencyPackage":{"id":"package_types:golang","type":"golang","namespaces":[{"id":"package_namespaces:golangguac-split-@@github.com/googleapis/gax-go","namespace":"github.com/googleapis/gax-go","names":[{"id":"package_names:ea417608-e3b0-5bfb-9889-95b0f158d525","name":"v2","versions":[{"id":"package_versions:6b60d487-2838-5ec8-b723-ff640f11db54","purl":"pkg:golang/github.com/googleapis/gax-go/v2@v2.1.0","version":"v2.1.0","qualifiers":[],"subpath":""}]}]}]},"dependencyType":"DIRECT","origin":"deps.dev","collector":"deps.dev"},{"id":"dependencies:4bb968b8-4cd8-55a3-b0e6-01d7ca061a84","justification":"dependency data collected via deps.dev","package":{"id":"package_types:golang","type":"golang","namespaces":[{"id":"package_namespaces:golangguac-split-@@cloud.google.com","namespace":"cloud.google.com","names":[{"id":"package_names:0c47e8bd-f53b-556f-8794-11506c98d268","name":"go","versions":[{"id":"package_versions:6c9a5bc9-097f-55ab-a7b0-937f2be892c2","purl":"pkg:golang/cloud.google.com/go@v0.97.0","version":"v0.97.0","qualifiers":[],"subpath":""}]}]}]},"dependencyPackage":{"id":"package_types:golang","type":"golang","namespaces":[{"id":"package_namespaces:golangguac-split-@@","namespace":"","names":[{"id":"package_names:b3b4b1d9-a334-5a3b-b636-88b080edba06","name":"go.opencensus.io","versions":[{"id":"package_versions:4c42e74c-4502-5f60-8974-c2f80fdf5eaf","purl":"pkg:golang/go.opencensus.io@v0.23.0","version":"v0.23.0","qualifiers":[],"subpath":""}]}]}]},"dependencyType":"DIRECT","origin":"deps.dev","collector":"deps.dev"},{"id":"dependencies:b7db1e45-e4a5-5d39-9282-05d6b31ec4b0","justification":"dependency data collected via deps.dev","package":{"id":"package_types:golang","type":"golang","namespaces":[{"id":"package_namespaces:golangguac-split-@@cloud.google.com","namespace":"cloud.google.com","names":[{"id":"package_names:0c47e8bd-f53b-556f-8794-11506c98d268","name":"go","versions":[{"id":"package_versions:6c9a5bc9-097f-55ab-a7b0-937f2be892c2","purl":"pkg:golang/cloud.google.com/go@v0.97.0","version":"v0.97.0","qualifiers":[],"subpath":""}]}]}]},"dependencyPackage":{"id":"package_types:golang","type":"golang","namespaces":[{"id":"package_namespaces:golangguac-split-@@golang.org/x","namespace":"golang.org/x","names":[{"id":"package_names:1c7c772b-8d57-5337-a23e-5180e6144a9a","name":"oauth2","versions":[{"id":"package_versions:1e573995-657f-55f1-86e8-cbd0c69cd52c","purl":"pkg:golang/golang.org/x/oauth2@v0.0.0-20210819190943-2bc19b11175f","version":"v0.0.0-20210819190943-2bc19b11175f","qualifiers":[],"subpath":""}]}]}]},"dependencyType":"DIRECT","origin":"deps.dev","collector":"deps.dev"},{"id":"dependencies:41b75245-08f2-54bf-8c97-4c6d3e269ff3","justification":"dependency data collected via deps.dev","package":{"id":"package_types:golang","type":"golang","namespaces":[{"id":"package_namespaces:golangguac-split-@@cloud.google.com","namespace":"cloud.google.com","names":[{"id":"package_names:0c47e8bd-f53b-556f-8794-11506c98d268","name":"go","versions":[{"id":"package_versions:6c9a5bc9-097f-55ab-a7b0-937f2be892c2","purl":"pkg:golang/cloud.google.com/go@v0.97.0","version":"v0.97.0","qualifiers":[],"subpath":""}]}]}]},"dependencyPackage":{"id":"package_types:golang","type":"golang","namespaces":[{"id":"package_namespaces:golangguac-split-@@golang.org/x","namespace":"golang.org/x","names":[{"id":"package_names:f7730425-ecf7-55a4-84ea-62392d8d5749","name":"xerrors","versions":[{"id":"package_versions:ccbe0b17-a320-5b1c-9cf8-2453828468e1","purl":"pkg:golang/golang.org/x/xerrors@v0.0.0-20200804184101-5ec99f83aff1","version":"v0.0.0-20200804184101-5ec99f83aff1","qualifiers":[],"subpath":""}]}]}]},"dependencyType":"DIRECT","origin":"deps.dev","collector":"deps.dev"},{"id":"dependencies:fc46b20f-5cb1-5939-a046-638427f339f7","justification":"dependency data collected via deps.dev","package":{"id":"package_types:golang","type":"golang","namespaces":[{"id":"package_namespaces:golangguac-split-@@cloud.google.com","namespace":"cloud.google.com","names":[{"id":"package_names:0c47e8bd-f53b-556f-8794-11506c98d268","name":"go","versions":[{"id":"package_versions:6c9a5bc9-097f-55ab-a7b0-937f2be892c2","purl":"pkg:golang/cloud.google.com/go@v0.97.0","version":"v0.97.0","qualifiers":[],"subpath":""}]}]}]},"dependencyPackage":{"id":"package_types:golang","type":"golang","namespaces":[{"id":"package_namespaces:golangguac-split-@@google.golang.org","namespace":"google.golang.org","names":[{"id":"package_names:574d6a3b-6036-55d4-ae5b-f313de75887b","name":"api","versions":[{"id":"package_versions:f3694f55-063e-54c9-9d8b-cbb45f87f9ae","purl":"pkg:golang/google.golang.org/api@v0.57.0","version":"v0.57.0","qualifiers":[],"subpath":""}]}]}]},"dependencyType":"DIRECT","origin":"deps.dev","collector":"deps.dev"},{"id":"dependencies:e4dd052c-962b-54b1-9240-5ddec69d3546","justification":"dependency data collected via deps.dev","package":{"id":"package_types:golang","type":"golang","namespaces":[{"id":"package_namespaces:golangguac-split-@@cloud.google.com","namespace":"cloud.google.com","names":[{"id":"package_names:0c47e8bd-f53b-556f-8794-11506c98d268","name":"go","versions":[{"id":"package_versions:6c9a5bc9-097f-55ab-a7b0-937f2be892c2","purl":"pkg:golang/cloud.google.com/go@v0.97.0","version":"v0.97.0","qualifiers":[],"subpath":""}]}]}]},"dependencyPackage":{"id":"package_types:golang","type":"golang","namespaces":[{"id":"package_namespaces:golangguac-split-@@google.golang.org","namespace":"google.golang.org","names":[{"id":"package_names:c1c08a0f-8baa-539c-91ad-f5e143249f4b","name":"genproto","versions":[{"id":"package_versions:bb1b4307-9171-5960-8539-859ef923ade0","purl":"pkg:golang/google.golang.org/genproto@v0.0.0-20210924002016-3dee208752a0","version":"v0.0.0-20210924002016-3dee208752a0","qualifiers":[],"subpath":""}]}]}]},"dependencyType":"DIRECT","origin":"deps.dev","collector":"deps.dev"},{"id":"dependencies:67363cd0-8644-5cc3-a4e6-3cc48218c66c","justification":"dependency data collected via deps.dev","package":{"id":"package_types:golang","type":"golang","namespaces":[{"id":"package_namespaces:golangguac-split-@@cloud.google.com","namespace":"cloud.google.com","names":[{"id":"package_names:0c47e8bd-f53b-556f-8794-11506c98d268","name":"go","versions":[{"id":"package_versions:6c9a5bc9-097f-55ab-a7b0-937f2be892c2","purl":"pkg:golang/cloud.google.com/go@v0.97.0","version":"v0.97.0","qualifiers":[],"subpath":""}]}]}]},"dependencyPackage":{"id":"package_types:golang","type":"golang","namespaces":[{"id":"package_namespaces:golangguac-split-@@google.golang.org","namespace":"google.golang.org","names":[{"id":"package_names:2dc79dd0-c1ee-528a-a1a8-7c34d7d70cf4","name":"grpc","versions":[{"id":"package_versions:3532d212-49c1-5312-81e0-934288dbff6f","purl":"pkg:golang/google.golang.org/grpc@v1.40.0","version":"v1.40.0","qualifiers":[],"subpath":""}]}]}]},"dependencyType":"DIRECT","origin":"deps.dev","collector":"deps.dev"},{"id":"dependencies:958aa22b-f029-52cc-92fe-14a7e1ad5de0","justification":"dependency data collected via deps.dev","package":{"id":"package_types:golang","type":"golang","namespaces":[{"id":"package_namespaces:golangguac-split-@@cloud.google.com","namespace":"cloud.google.com","names":[{"id":"package_names:0c47e8bd-f53b-556f-8794-11506c98d268","name":"go","versions":[{"id":"package_versions:6c9a5bc9-097f-55ab-a7b0-937f2be892c2","purl":"pkg:golang/cloud.google.com/go@v0.97.0","version":"v0.97.0","qualifiers":[],"subpath":""}]}]}]},"dependencyPackage":{"id":"package_types:golang","type":"golang","namespaces":[{"id":"package_namespaces:golangguac-split-@@google.golang.org","namespace":"google.golang.org","names":[{"id":"package_names:4833fe40-e306-5891-a53c-dda7e8f6d5fc","name":"protobuf","versions":[{"id":"package_versions:be59d0a9-9c01-5106-82f2-216581252279","purl":"pkg:golang/google.golang.org/protobuf@v1.27.1","version":"v1.27.1","qualifiers":[],"subpath":""}]}]}]},"dependencyType":"DIRECT","origin":"deps.dev","collector":"deps.dev"},{"id":"dependencies:bdea256b-c668-5fb2-9ee4-ddd8f1fc75a3","justification":"dependency data collected via deps.dev","package":{"id":"package_types:golang","type":"golang","namespaces":[{"id":"package_namespaces:golangguac-split-@@cloud.google.com/go","namespace":"cloud.google.com/go","names":[{"id":"package_names:076437cc-3046-55f2-b2ac-e1cf018c5dbc","name":"storage","versions":[{"id":"package_versions:b8289d60-77da-52d7-a3c5-25f09a834c7b","purl":"pkg:golang/cloud.google.com/go/storage@v1.10.0","version":"v1.10.0","qualifiers":[],"subpath":""}]}]}]},"dependencyPackage":{"id":"package_types:golang","type":"golang","namespaces":[{"id":"package_namespaces:golangguac-split-@@cloud.google.com","namespace":"cloud.google.com","names":[{"id":"package_names:0c47e8bd-f53b-556f-8794-11506c98d268","name":"go","versions":[{"id":"package_versions:6c9a5bc9-097f-55ab-a7b0-937f2be892c2","purl":"pkg:golang/cloud.google.com/go@v0.97.0","version":"v0.97.0","qualifiers":[],"subpath":""}]}]}]},"dependencyType":"DIRECT","origin":"deps.dev","collector":"deps.dev"},{"id":"dependencies:9449d967-24d4-554e-8389-c8f986600a38","justification":"dependency data collected via deps.dev","package":{"id":"package_types:golang","type":"golang","namespaces":[{"id":"package_namespaces:golangguac-split-@@cloud.google.com/go","namespace":"cloud.google.com/go","names":[{"id":"package_names:076437cc-3046-55f2-b2ac-e1cf018c5dbc","name":"storage","versions":[{"id":"package_versions:b8289d60-77da-52d7-a3c5-25f09a834c7b","purl":"pkg:golang/cloud.google.com/go/storage@v1.10.0","version":"v1.10.0","qualifiers":[],"subpath":""}]}]}]},"dependencyPackage":{"id":"package_types:golang","type":"golang","namespaces":[{"id":"package_namespaces:golangguac-split-@@github.com/googleapis/gax-go","namespace":"github.com/googleapis/gax-go","names":[{"id":"package_names:ea417608-e3b0-5bfb-9889-95b0f158d525","name":"v2","versions":[{"id":"package_versions:6b60d487-2838-5ec8-b723-ff640f11db54","purl":"pkg:golang/github.com/googleapis/gax-go/v2@v2.1.0","version":"v2.1.0","qualifiers":[],"subpath":""}]}]}]},"dependencyType":"DIRECT","origin":"deps.dev","collector":"deps.dev"},{"id":"dependencies:5f043bc8-e16a-52f1-b990-b8847768f6a2","justification":"dependency data collected via deps.dev","package":{"id":"package_types:golang","type":"golang","namespaces":[{"id":"package_namespaces:golangguac-split-@@cloud.google.com/go","namespace":"cloud.google.com/go","names":[{"id":"package_names:076437cc-3046-55f2-b2ac-e1cf018c5dbc","name":"storage","versions":[{"id":"package_versions:b8289d60-77da-52d7-a3c5-25f09a834c7b","purl":"pkg:golang/cloud.google.com/go/storage@v1.10.0","version":"v1.10.0","qualifiers":[],"subpath":""}]}]}]},"dependencyPackage":{"id":"package_types:golang","type":"golang","namespaces":[{"id":"package_namespaces:golangguac-split-@@google.golang.org","namespace":"google.golang.org","names":[{"id":"package_names:574d6a3b-6036-55d4-ae5b-f313de75887b","name":"api","versions":[{"id":"package_versions:f3694f55-063e-54c9-9d8b-cbb45f87f9ae","purl":"pkg:golang/google.golang.org/api@v0.57.0","version":"v0.57.0","qualifiers":[],"subpath":""}]}]}]},"dependencyType":"DIRECT","origin":"deps.dev","collector":"deps.dev"},{"id":"dependencies:11b45ea4-c9d8-5520-ab7a-5c64cbe70cc6","justification":"dependency data collected via deps.dev","package":{"id":"package_types:golang","type":"golang","namespaces":[{"id":"package_namespaces:golangguac-split-@@cloud.google.com/go","namespace":"cloud.google.com/go","names":[{"id":"package_names:076437cc-3046-55f2-b2ac-e1cf018c5dbc","name":"storage","versions":[{"id":"package_versions:b8289d60-77da-52d7-a3c5-25f09a834c7b","purl":"pkg:golang/cloud.google.com/go/storage@v1.10.0","version":"v1.10.0","qualifiers":[],"subpath":""}]}]}]},"dependencyPackage":{"id":"package_types:golang","type":"golang","namespaces":[{"id":"package_namespaces:golangguac-split-@@google.golang.org","namespace":"google.golang.org","names":[{"id":"package_names:c1c08a0f-8baa-539c-91ad-f5e143249f4b","name":"genproto","versions":[{"id":"package_versions:bb1b4307-9171-5960-8539-859ef923ade0","purl":"pkg:golang/google.golang.org/genproto@v0.0.0-20210924002016-3dee208752a0","version":"v0.0.0-20210924002016-3dee208752a0","qualifiers":[],"subpath":""}]}]}]},"dependencyType":"DIRECT","origin":"deps.dev","collector":"deps.dev"},{"id":"dependencies:9133ebef-00b8-5f1c-8368-25a8416aecc3","justification":"dependency data collected via deps.dev","package":{"id":"package_types:golang","type":"golang","namespaces":[{"id":"package_namespaces:golangguac-split-@@github.com/golang","namespace":"github.com/golang","names":[{"id":"package_names:320a482a-3ad7-5a14-ad48-9304da558d41","name":"protobuf","versions":[{"id":"package_versions:59ba7431-d04d-5b33-b4be-ef0b31a54b94","purl":"pkg:golang/github.com/golang/protobuf@v1.5.2","version":"v1.5.2","qualifiers":[],"subpath":""}]}]}]},"dependencyPackage":{"id":"package_types:golang","type":"golang","namespaces":[{"id":"package_namespaces:golangguac-split-@@google.golang.org","namespace":"google.golang.org","names":[{"id":"package_names:4833fe40-e306-5891-a53c-dda7e8f6d5fc","name":"protobuf","versions":[{"id":"package_versions:be59d0a9-9c01-5106-82f2-216581252279","purl":"pkg:golang/google.golang.org/protobuf@v1.27.1","version":"v1.27.1","qualifiers":[],"subpath":""}]}]}]},"dependencyType":"DIRECT","origin":"deps.dev","collector":"deps.dev"},{"id":"dependencies:5d19e486-4f72-5520-9729-e6de62069226","justification":"dependency data collected via deps.dev","package":{"id":"package_types:golang","type":"golang","namespaces":[{"id":"package_namespaces:golangguac-split-@@github.com/google","namespace":"github.com/google","names":[{"id":"package_names:238c18ee-09d5-56bf-bc39-78997eb030f3","name":"go-cmp","versions":[{"id":"package_versions:79827ed9-63b5-5388-a107-aa05bedab549","purl":"pkg:golang/github.com/google/go-cmp@v0.5.6","version":"v0.5.6","qualifiers":[],"subpath":""}]}]}]},"dependencyPackage":{"id":"package_types:golang","type":"golang","namespaces":[{"id":"package_namespaces:golangguac-split-@@golang.org/x","namespace":"golang.org/x","names":[{"id":"package_names:f7730425-ecf7-55a4-84ea-62392d8d5749","name":"xerrors","versions":[{"id":"package_versions:ccbe0b17-a320-5b1c-9cf8-2453828468e1","purl":"pkg:golang/golang.org/x/xerrors@v0.0.0-20200804184101-5ec99f83aff1","version":"v0.0.0-20200804184101-5ec99f83aff1","qualifiers":[],"subpath":""}]}]}]},"dependencyType":"DIRECT","origin":"deps.dev","collector":"deps.dev"},{"id":"dependencies:7e622e78-349d-5111-96e6-81633e317a4d","justification":"dependency data collected via deps.dev","package":{"id":"package_types:golang","type":"golang","namespaces":[{"id":"package_namespaces:golangguac-split-@@github.com/google/martian","namespace":"github.com/google/martian","names":[{"id":"package_names:a57a9626-1438-5d74-9321-bb5b15a6bb4b","name":"v3","versions":[{"id":"package_versions:205cc45a-f352-54fd-905d-b603026caecf","purl":"pkg:golang/github.com/google/martian/v3@v3.2.1","version":"v3.2.1","qualifiers":[],"subpath":""}]}]}]},"dependencyPackage":{"id":"package_types:golang","type":"golang","namespaces":[{"id":"package_namespaces:golangguac-split-@@golang.org/x","namespace":"golang.org/x","names":[{"id":"package_names:10660366-cd81-5fa5-9ed3-5750e84e996e","name":"net","versions":[{"id":"package_versions:b0d4fdab-a6ad-5edc-8442-d8785917bcdd","purl":"pkg:golang/golang.org/x/net@v0.0.0-20210503060351-7fd8e65b6420","version":"v0.0.0-20210503060351-7fd8e65b6420","qualifiers":[],"subpath":""}]}]}]},"dependencyType":"DIRECT","origin":"deps.dev","collector":"deps.dev"},{"id":"dependencies:c789f95b-7d46-5919-9ff6-ea6531df2e78","justification":"dependency data collected via deps.dev","package":{"id":"package_types:golang","type":"golang","namespaces":[{"id":"package_namespaces:golangguac-split-@@github.com/googleapis/gax-go","namespace":"github.com/googleapis/gax-go","names":[{"id":"package_names:ea417608-e3b0-5bfb-9889-95b0f158d525","name":"v2","versions":[{"id":"package_versions:6b60d487-2838-5ec8-b723-ff640f11db54","purl":"pkg:golang/github.com/googleapis/gax-go/v2@v2.1.0","version":"v2.1.0","qualifiers":[],"subpath":""}]}]}]},"dependencyPackage":{"id":"package_types:golang","type":"golang","namespaces":[{"id":"package_namespaces:golangguac-split-@@google.golang.org","namespace":"google.golang.org","names":[{"id":"package_names:574d6a3b-6036-55d4-ae5b-f313de75887b","name":"api","versions":[{"id":"package_versions:f3694f55-063e-54c9-9d8b-cbb45f87f9ae","purl":"pkg:golang/google.golang.org/api@v0.57.0","version":"v0.57.0","qualifiers":[],"subpath":""}]}]}]},"dependencyType":"DIRECT","origin":"deps.dev","collector":"deps.dev"},{"id":"dependencies:b171e49c-7425-5ffb-97b6-32d34ce811a6","justification":"dependency data collected via deps.dev","package":{"id":"package_types:golang","type":"golang","namespaces":[{"id":"package_namespaces:golangguac-split-@@github.com/googleapis/gax-go","namespace":"github.com/googleapis/gax-go","names":[{"id":"package_names:ea417608-e3b0-5bfb-9889-95b0f158d525","name":"v2","versions":[{"id":"package_versions:6b60d487-2838-5ec8-b723-ff640f11db54","purl":"pkg:golang/github.com/googleapis/gax-go/v2@v2.1.0","version":"v2.1.0","qualifiers":[],"subpath":""}]}]}]},"dependencyPackage":{"id":"package_types:golang","type":"golang","namespaces":[{"id":"package_namespaces:golangguac-split-@@google.golang.org","namespace":"google.golang.org","names":[{"id":"package_names:c1c08a0f-8baa-539c-91ad-f5e143249f4b","name":"genproto","versions":[{"id":"package_versions:bb1b4307-9171-5960-8539-859ef923ade0","purl":"pkg:golang/google.golang.org/genproto@v0.0.0-20210924002016-3dee208752a0","version":"v0.0.0-20210924002016-3dee208752a0","qualifiers":[],"subpath":""}]}]}]},"dependencyType":"DIRECT","origin":"deps.dev","collector":"deps.dev"},{"id":"dependencies:50099ac0-745a-5b0f-85db-ee302ec8c14f","justification":"dependency data collected via deps.dev","package":{"id":"package_types:golang","type":"golang","namespaces":[{"id":"package_namespaces:golangguac-split-@@github.com/googleapis/gax-go","namespace":"github.com/googleapis/gax-go","names":[{"id":"package_names:ea417608-e3b0-5bfb-9889-95b0f158d525","name":"v2","versions":[{"id":"package_versions:6b60d487-2838-5ec8-b723-ff640f11db54","purl":"pkg:golang/github.com/googleapis/gax-go/v2@v2.1.0","version":"v2.1.0","qualifiers":[],"subpath":""}]}]}]},"dependencyPackage":{"id":"package_types:golang","type":"golang","namespaces":[{"id":"package_namespaces:golangguac-split-@@google.golang.org","namespace":"google.golang.org","names":[{"id":"package_names:2dc79dd0-c1ee-528a-a1a8-7c34d7d70cf4","name":"grpc","versions":[{"id":"package_versions:3532d212-49c1-5312-81e0-934288dbff6f","purl":"pkg:golang/google.golang.org/grpc@v1.40.0","version":"v1.40.0","qualifiers":[],"subpath":""}]}]}]},"dependencyType":"DIRECT","origin":"deps.dev","collector":"deps.dev"},{"id":"dependencies:e0a77de5-f8fe-5d65-ba7a-24ee402c7994","justification":"dependency data collected via deps.dev","package":{"id":"package_types:golang","type":"golang","namespaces":[{"id":"package_namespaces:golangguac-split-@@github.com/googleapis/gax-go","namespace":"github.com/googleapis/gax-go","names":[{"id":"package_names:ea417608-e3b0-5bfb-9889-95b0f158d525","name":"v2","versions":[{"id":"package_versions:6b60d487-2838-5ec8-b723-ff640f11db54","purl":"pkg:golang/github.com/googleapis/gax-go/v2@v2.1.0","version":"v2.1.0","qualifiers":[],"subpath":""}]}]}]},"dependencyPackage":{"id":"package_types:golang","type":"golang","namespaces":[{"id":"package_namespaces:golangguac-split-@@google.golang.org","namespace":"google.golang.org","names":[{"id":"package_names:4833fe40-e306-5891-a53c-dda7e8f6d5fc","name":"protobuf","versions":[{"id":"package_versions:be59d0a9-9c01-5106-82f2-216581252279","purl":"pkg:golang/google.golang.org/protobuf@v1.27.1","version":"v1.27.1","qualifiers":[],"subpath":""}]}]}]},"dependencyType":"DIRECT","origin":"deps.dev","collector":"deps.dev"},{"id":"dependencies:0a10b433-96e1-5b25-aeec-f8fbab0d0aac","justification":"dependency data collected via deps.dev","package":{"id":"package_types:golang","type":"golang","namespaces":[{"id":"package_namespaces:golangguac-split-@@","namespace":"","names":[{"id":"package_names:b3b4b1d9-a334-5a3b-b636-88b080edba06","name":"go.opencensus.io","versions":[{"id":"package_versions:4c42e74c-4502-5f60-8974-c2f80fdf5eaf","purl":"pkg:golang/go.opencensus.io@v0.23.0","version":"v0.23.0","qualifiers":[],"subpath":""}]}]}]},"dependencyPackage":{"id":"package_types:golang","type":"golang","namespaces":[{"id":"package_namespaces:golangguac-split-@@github.com/golang","namespace":"github.com/golang","names":[{"id":"package_names:4cfb47fa-723f-535e-a84f-7ea9670c1b1b","name":"groupcache","versions":[{"id":"package_versions:50b2a3e6-916a-5079-a9ab-a46ef67a0cf9","purl":"pkg:golang/github.com/golang/groupcache@v0.0.0-20200121045136-8c9f03a8e57e","version":"v0.0.0-20200121045136-8c9f03a8e57e","qualifiers":[],"subpath":""}]}]}]},"dependencyType":"DIRECT","origin":"deps.dev","collector":"deps.dev"},{"id":"dependencies:6211441d-316c-58fc-ac8f-76ca23f33057","justification":"dependency data collected via deps.dev","package":{"id":"package_types:golang","type":"golang","namespaces":[{"id":"package_namespaces:golangguac-split-@@","namespace":"","names":[{"id":"package_names:b3b4b1d9-a334-5a3b-b636-88b080edba06","name":"go.opencensus.io","versions":[{"id":"package_versions:4c42e74c-4502-5f60-8974-c2f80fdf5eaf","purl":"pkg:golang/go.opencensus.io@v0.23.0","version":"v0.23.0","qualifiers":[],"subpath":""}]}]}]},"dependencyPackage":{"id":"package_types:golang","type":"golang","namespaces":[{"id":"package_namespaces:golangguac-split-@@google.golang.org","namespace":"google.golang.org","names":[{"id":"package_names:2dc79dd0-c1ee-528a-a1a8-7c34d7d70cf4","name":"grpc","versions":[{"id":"package_versions:3532d212-49c1-5312-81e0-934288dbff6f","purl":"pkg:golang/google.golang.org/grpc@v1.40.0","version":"v1.40.0","qualifiers":[],"subpath":""}]}]}]},"dependencyType":"DIRECT","origin":"deps.dev","collector":"deps.dev"},{"id":"dependencies:ceb892ee-80b6-5cb6-af47-640c77a64ed7","justification":"dependency data collected via deps.dev","package":{"id":"package_types:golang","type":"golang","namespaces":[{"id":"package_namespaces:golangguac-split-@@golang.org/x","namespace":"golang.org/x","names":[{"id":"package_names:10660366-cd81-5fa5-9ed3-5750e84e996e","name":"net","versions":[{"id":"package_versions:b0d4fdab-a6ad-5edc-8442-d8785917bcdd","purl":"pkg:golang/golang.org/x/net@v0.0.0-20210503060351-7fd8e65b6420","version":"v0.0.0-20210503060351-7fd8e65b6420","qualifiers":[],"subpath":""}]}]}]},"dependencyPackage":{"id":"package_types:golang","type":"golang","namespaces":[{"id":"package_namespaces:golangguac-split-@@golang.org/x","namespace":"golang.org/x","names":[{"id":"package_names:dc25e99a-787e-5afb-9222-fa36a50e3b01","name":"text","versions":[{"id":"package_versions:e4b70ee4-4510-5052-8060-90dc4be40754","purl":"pkg:golang/golang.org/x/text@v0.3.6","version":"v0.3.6","qualifiers":[],"subpath":""}]}]}]},"dependencyType":"DIRECT","origin":"deps.dev","collector":"deps.dev"},{"id":"dependencies:d96c59d1-e612-5cd1-bac6-b7f5a2a21430","justification":"dependency data collected via deps.dev","package":{"id":"package_types:golang","type":"golang","namespaces":[{"id":"package_namespaces:golangguac-split-@@golang.org/x","namespace":"golang.org/x","names":[{"id":"package_names:1c7c772b-8d57-5337-a23e-5180e6144a9a","name":"oauth2","versions":[{"id":"package_versions:1e573995-657f-55f1-86e8-cbd0c69cd52c","purl":"pkg:golang/golang.org/x/oauth2@v0.0.0-20210819190943-2bc19b11175f","version":"v0.0.0-20210819190943-2bc19b11175f","qualifiers":[],"subpath":""}]}]}]},"dependencyPackage":{"id":"package_types:golang","type":"golang","namespaces":[{"id":"package_namespaces:golangguac-split-@@cloud.google.com","namespace":"cloud.google.com","names":[{"id":"package_names:0c47e8bd-f53b-556f-8794-11506c98d268","name":"go","versions":[{"id":"package_versions:6c9a5bc9-097f-55ab-a7b0-937f2be892c2","purl":"pkg:golang/cloud.google.com/go@v0.97.0","version":"v0.97.0","qualifiers":[],"subpath":""}]}]}]},"dependencyType":"DIRECT","origin":"deps.dev","collector":"deps.dev"},{"id":"dependencies:df6baa60-e8d5-5c5c-bb91-814fc19c9595","justification":"dependency data collected via deps.dev","package":{"id":"package_types:golang","type":"golang","namespaces":[{"id":"package_namespaces:golangguac-split-@@golang.org/x","namespace":"golang.org/x","names":[{"id":"package_names:1c7c772b-8d57-5337-a23e-5180e6144a9a","name":"oauth2","versions":[{"id":"package_versions:1e573995-657f-55f1-86e8-cbd0c69cd52c","purl":"pkg:golang/golang.org/x/oauth2@v0.0.0-20210819190943-2bc19b11175f","version":"v0.0.0-20210819190943-2bc19b11175f","qualifiers":[],"subpath":""}]}]}]},"dependencyPackage":{"id":"package_types:golang","type":"golang","namespaces":[{"id":"package_namespaces:golangguac-split-@@golang.org/x","namespace":"golang.org/x","names":[{"id":"package_names:10660366-cd81-5fa5-9ed3-5750e84e996e","name":"net","versions":[{"id":"package_versions:b0d4fdab-a6ad-5edc-8442-d8785917bcdd","purl":"pkg:golang/golang.org/x/net@v0.0.0-20210503060351-7fd8e65b6420","version":"v0.0.0-20210503060351-7fd8e65b6420","qualifiers":[],"subpath":""}]}]}]},"dependencyType":"DIRECT","origin":"deps.dev","collector":"deps.dev"},{"id":"dependencies:47b1f0ac-3bdd-5f92-ae95-a58ea7775a53","justification":"dependency data collected via deps.dev","package":{"id":"package_types:golang","type":"golang","namespaces":[{"id":"package_namespaces:golangguac-split-@@golang.org/x","namespace":"golang.org/x","names":[{"id":"package_names:1c7c772b-8d57-5337-a23e-5180e6144a9a","name":"oauth2","versions":[{"id":"package_versions:1e573995-657f-55f1-86e8-cbd0c69cd52c","purl":"pkg:golang/golang.org/x/oauth2@v0.0.0-20210819190943-2bc19b11175f","version":"v0.0.0-20210819190943-2bc19b11175f","qualifiers":[],"subpath":""}]}]}]},"dependencyPackage":{"id":"package_types:golang","type":"golang","namespaces":[{"id":"package_namespaces:golangguac-split-@@google.golang.org","namespace":"google.golang.org","names":[{"id":"package_names:3f25aec7-5b95-5d8e-b51c-1046029359b2","name":"appengine","versions":[{"id":"package_versions:45b1d4fc-7f94-5973-9595-af0628662e22","purl":"pkg:golang/google.golang.org/appengine@v1.6.7","version":"v1.6.7","qualifiers":[],"subpath":""}]}]}]},"dependencyType":"DIRECT","origin":"deps.dev","collector":"deps.dev"},{"id":"dependencies:6b4de568-3874-50dd-b7bc-9bb273471abf","justification":"dependency data collected via deps.dev","package":{"id":"package_types:golang","type":"golang","namespaces":[{"id":"package_namespaces:golangguac-split-@@google.golang.org","namespace":"google.golang.org","names":[{"id":"package_names:574d6a3b-6036-55d4-ae5b-f313de75887b","name":"api","versions":[{"id":"package_versions:f3694f55-063e-54c9-9d8b-cbb45f87f9ae","purl":"pkg:golang/google.golang.org/api@v0.57.0","version":"v0.57.0","qualifiers":[],"subpath":""}]}]}]},"dependencyPackage":{"id":"package_types:golang","type":"golang","namespaces":[{"id":"package_namespaces:golangguac-split-@@cloud.google.com","namespace":"cloud.google.com","names":[{"id":"package_names:0c47e8bd-f53b-556f-8794-11506c98d268","name":"go","versions":[{"id":"package_versions:6c9a5bc9-097f-55ab-a7b0-937f2be892c2","purl":"pkg:golang/cloud.google.com/go@v0.97.0","version":"v0.97.0","qualifiers":[],"subpath":""}]}]}]},"dependencyType":"DIRECT","origin":"deps.dev","collector":"deps.dev"},{"id":"dependencies:34b6e39f-ef3e-525b-8c5d-547446b341d7","justification":"dependency data collected via deps.dev","package":{"id":"package_types:golang","type":"golang","namespaces":[{"id":"package_namespaces:golangguac-split-@@google.golang.org","namespace":"google.golang.org","names":[{"id":"package_names:574d6a3b-6036-55d4-ae5b-f313de75887b","name":"api","versions":[{"id":"package_versions:f3694f55-063e-54c9-9d8b-cbb45f87f9ae","purl":"pkg:golang/google.golang.org/api@v0.57.0","version":"v0.57.0","qualifiers":[],"subpath":""}]}]}]},"dependencyPackage":{"id":"package_types:golang","type":"golang","namespaces":[{"id":"package_namespaces:golangguac-split-@@github.com/googleapis/gax-go","namespace":"github.com/googleapis/gax-go","names":[{"id":"package_names:ea417608-e3b0-5bfb-9889-95b0f158d525","name":"v2","versions":[{"id":"package_versions:6b60d487-2838-5ec8-b723-ff640f11db54","purl":"pkg:golang/github.com/googleapis/gax-go/v2@v2.1.0","version":"v2.1.0","qualifiers":[],"subpath":""}]}]}]},"dependencyType":"DIRECT","origin":"deps.dev","collector":"deps.dev"},{"id":"dependencies:b9bde93c-bee1-5a43-abd2-b20dcfd7add2","justification":"dependency data collected via deps.dev","package":{"id":"package_types:golang","type":"golang","namespaces":[{"id":"package_namespaces:golangguac-split-@@google.golang.org","namespace":"google.golang.org","names":[{"id":"package_names:574d6a3b-6036-55d4-ae5b-f313de75887b","name":"api","versions":[{"id":"package_versions:f3694f55-063e-54c9-9d8b-cbb45f87f9ae","purl":"pkg:golang/google.golang.org/api@v0.57.0","version":"v0.57.0","qualifiers":[],"subpath":""}]}]}]},"dependencyPackage":{"id":"package_types:golang","type":"golang","namespaces":[{"id":"package_namespaces:golangguac-split-@@","namespace":"","names":[{"id":"package_names:b3b4b1d9-a334-5a3b-b636-88b080edba06","name":"go.opencensus.io","versions":[{"id":"package_versions:4c42e74c-4502-5f60-8974-c2f80fdf5eaf","purl":"pkg:golang/go.opencensus.io@v0.23.0","version":"v0.23.0","qualifiers":[],"subpath":""}]}]}]},"dependencyType":"DIRECT","origin":"deps.dev","collector":"deps.dev"},{"id":"dependencies:e90742b6-5489-5c4c-933b-0cf78fdc393c","justification":"dependency data collected via deps.dev","package":{"id":"package_types:golang","type":"golang","namespaces":[{"id":"package_namespaces:golangguac-split-@@google.golang.org","namespace":"google.golang.org","names":[{"id":"package_names:574d6a3b-6036-55d4-ae5b-f313de75887b","name":"api","versions":[{"id":"package_versions:f3694f55-063e-54c9-9d8b-cbb45f87f9ae","purl":"pkg:golang/google.golang.org/api@v0.57.0","version":"v0.57.0","qualifiers":[],"subpath":""}]}]}]},"dependencyPackage":{"id":"package_types:golang","type":"golang","namespaces":[{"id":"package_namespaces:golangguac-split-@@golang.org/x","namespace":"golang.org/x","names":[{"id":"package_names:10660366-cd81-5fa5-9ed3-5750e84e996e","name":"net","versions":[{"id":"package_versions:b0d4fdab-a6ad-5edc-8442-d8785917bcdd","purl":"pkg:golang/golang.org/x/net@v0.0.0-20210503060351-7fd8e65b6420","version":"v0.0.0-20210503060351-7fd8e65b6420","qualifiers":[],"subpath":""}]}]}]},"dependencyType":"DIRECT","origin":"deps.dev","collector":"deps.dev"},{"id":"dependencies:fb9171ba-7b73-5428-a703-90812e5cccfd","justification":"dependency data collected via deps.dev","package":{"id":"package_types:golang","type":"golang","namespaces":[{"id":"package_namespaces:golangguac-split-@@google.golang.org","namespace":"google.golang.org","names":[{"id":"package_names:574d6a3b-6036-55d4-ae5b-f313de75887b","name":"api","versions":[{"id":"package_versions:f3694f55-063e-54c9-9d8b-cbb45f87f9ae","purl":"pkg:golang/google.golang.org/api@v0.57.0","version":"v0.57.0","qualifiers":[],"subpath":""}]}]}]},"dependencyPackage":{"id":"package_types:golang","type":"golang","namespaces":[{"id":"package_namespaces:golangguac-split-@@golang.org/x","namespace":"golang.org/x","names":[{"id":"package_names:1c7c772b-8d57-5337-a23e-5180e6144a9a","name":"oauth2","versions":[{"id":"package_versions:1e573995-657f-55f1-86e8-cbd0c69cd52c","purl":"pkg:golang/golang.org/x/oauth2@v0.0.0-20210819190943-2bc19b11175f","version":"v0.0.0-20210819190943-2bc19b11175f","qualifiers":[],"subpath":""}]}]}]},"dependencyType":"DIRECT","origin":"deps.dev","collector":"deps.dev"},{"id":"dependencies:44bde2e3-9d09-56a9-9c56-090fb08df893","justification":"dependency data collected via deps.dev","package":{"id":"package_types:golang","type":"golang","namespaces":[{"id":"package_namespaces:golangguac-split-@@google.golang.org","namespace":"google.golang.org","names":[{"id":"package_names:574d6a3b-6036-55d4-ae5b-f313de75887b","name":"api","versions":[{"id":"package_versions:f3694f55-063e-54c9-9d8b-cbb45f87f9ae","purl":"pkg:golang/google.golang.org/api@v0.57.0","version":"v0.57.0","qualifiers":[],"subpath":""}]}]}]},"dependencyPackage":{"id":"package_types:golang","type":"golang","namespaces":[{"id":"package_namespaces:golangguac-split-@@golang.org/x","namespace":"golang.org/x","names":[{"id":"package_names:6c0a9691-7a6f-5176-a395-cab080877631","name":"sys","versions":[{"id":"package_versions:23e077f5-164f-5824-94be-59a13126e7d8","purl":"pkg:golang/golang.org/x/sys@v0.0.0-20210908233432-aa78b53d3365","version":"v0.0.0-20210908233432-aa78b53d3365","qualifiers":[],"subpath":""}]}]}]},"dependencyType":"DIRECT","origin":"deps.dev","collector":"deps.dev"},{"id":"dependencies:a316c0cb-24de-564f-a299-6804cd3fa941","justification":"dependency data collected via deps.dev","package":{"id":"package_types:golang","type":"golang","namespaces":[{"id":"package_namespaces:golangguac-split-@@google.golang.org","namespace":"google.golang.org","names":[{"id":"package_names:574d6a3b-6036-55d4-ae5b-f313de75887b","name":"api","versions":[{"id":"package_versions:f3694f55-063e-54c9-9d8b-cbb45f87f9ae","purl":"pkg:golang/google.golang.org/api@v0.57.0","version":"v0.57.0","qualifiers":[],"subpath":""}]}]}]},"dependencyPackage":{"id":"package_types:golang","type":"golang","namespaces":[{"id":"package_namespaces:golangguac-split-@@google.golang.org","namespace":"google.golang.org","names":[{"id":"package_names:3f25aec7-5b95-5d8e-b51c-1046029359b2","name":"appengine","versions":[{"id":"package_versions:45b1d4fc-7f94-5973-9595-af0628662e22","purl":"pkg:golang/google.golang.org/appengine@v1.6.7","version":"v1.6.7","qualifiers":[],"subpath":""}]}]}]},"dependencyType":"DIRECT","origin":"deps.dev","collector":"deps.dev"},{"id":"dependencies:db0e3731-a025-56ef-9dbc-d7fb2b4916df","justification":"dependency data collected via deps.dev","package":{"id":"package_types:golang","type":"golang","namespaces":[{"id":"package_namespaces:golangguac-split-@@google.golang.org","namespace":"google.golang.org","names":[{"id":"package_names:574d6a3b-6036-55d4-ae5b-f313de75887b","name":"api","versions":[{"id":"package_versions:f3694f55-063e-54c9-9d8b-cbb45f87f9ae","purl":"pkg:golang/google.golang.org/api@v0.57.0","version":"v0.57.0","qualifiers":[],"subpath":""}]}]}]},"dependencyPackage":{"id":"package_types:golang","type":"golang","namespaces":[{"id":"package_namespaces:golangguac-split-@@google.golang.org","namespace":"google.golang.org","names":[{"id":"package_names:2dc79dd0-c1ee-528a-a1a8-7c34d7d70cf4","name":"grpc","versions":[{"id":"package_versions:3532d212-49c1-5312-81e0-934288dbff6f","purl":"pkg:golang/google.golang.org/grpc@v1.40.0","version":"v1.40.0","qualifiers":[],"subpath":""}]}]}]},"dependencyType":"DIRECT","origin":"deps.dev","collector":"deps.dev"},{"id":"dependencies:c0833a58-d706-5992-a9ac-7270b68bd6fb","justification":"dependency data collected via deps.dev","package":{"id":"package_types:golang","type":"golang","namespaces":[{"id":"package_namespaces:golangguac-split-@@google.golang.org","namespace":"google.golang.org","names":[{"id":"package_names:3f25aec7-5b95-5d8e-b51c-1046029359b2","name":"appengine","versions":[{"id":"package_versions:45b1d4fc-7f94-5973-9595-af0628662e22","purl":"pkg:golang/google.golang.org/appengine@v1.6.7","version":"v1.6.7","qualifiers":[],"subpath":""}]}]}]},"dependencyPackage":{"id":"package_types:golang","type":"golang","namespaces":[{"id":"package_namespaces:golangguac-split-@@github.com/golang","namespace":"github.com/golang","names":[{"id":"package_names:320a482a-3ad7-5a14-ad48-9304da558d41","name":"protobuf","versions":[{"id":"package_versions:59ba7431-d04d-5b33-b4be-ef0b31a54b94","purl":"pkg:golang/github.com/golang/protobuf@v1.5.2","version":"v1.5.2","qualifiers":[],"subpath":""}]}]}]},"dependencyType":"DIRECT","origin":"deps.dev","collector":"deps.dev"},{"id":"dependencies:42375da1-6ae8-5218-860d-337d4c73e7ec","justification":"dependency data collected via deps.dev","package":{"id":"package_types:golang","type":"golang","namespaces":[{"id":"package_namespaces:golangguac-split-@@google.golang.org","namespace":"google.golang.org","names":[{"id":"package_names:3f25aec7-5b95-5d8e-b51c-1046029359b2","name":"appengine","versions":[{"id":"package_versions:45b1d4fc-7f94-5973-9595-af0628662e22","purl":"pkg:golang/google.golang.org/appengine@v1.6.7","version":"v1.6.7","qualifiers":[],"subpath":""}]}]}]},"dependencyPackage":{"id":"package_types:golang","type":"golang","namespaces":[{"id":"package_namespaces:golangguac-split-@@golang.org/x","namespace":"golang.org/x","names":[{"id":"package_names:10660366-cd81-5fa5-9ed3-5750e84e996e","name":"net","versions":[{"id":"package_versions:b0d4fdab-a6ad-5edc-8442-d8785917bcdd","purl":"pkg:golang/golang.org/x/net@v0.0.0-20210503060351-7fd8e65b6420","version":"v0.0.0-20210503060351-7fd8e65b6420","qualifiers":[],"subpath":""}]}]}]},"dependencyType":"DIRECT","origin":"deps.dev","collector":"deps.dev"},{"id":"dependencies:06e815cd-e121-5577-b8ed-310aac1cf7bf","justification":"dependency data collected via deps.dev","package":{"id":"package_types:golang","type":"golang","namespaces":[{"id":"package_namespaces:golangguac-split-@@google.golang.org","namespace":"google.golang.org","names":[{"id":"package_names:c1c08a0f-8baa-539c-91ad-f5e143249f4b","name":"genproto","versions":[{"id":"package_versions:bb1b4307-9171-5960-8539-859ef923ade0","purl":"pkg:golang/google.golang.org/genproto@v0.0.0-20210924002016-3dee208752a0","version":"v0.0.0-20210924002016-3dee208752a0","qualifiers":[],"subpath":""}]}]}]},"dependencyPackage":{"id":"package_types:golang","type":"golang","namespaces":[{"id":"package_namespaces:golangguac-split-@@google.golang.org","namespace":"google.golang.org","names":[{"id":"package_names:2dc79dd0-c1ee-528a-a1a8-7c34d7d70cf4","name":"grpc","versions":[{"id":"package_versions:3532d212-49c1-5312-81e0-934288dbff6f","purl":"pkg:golang/google.golang.org/grpc@v1.40.0","version":"v1.40.0","qualifiers":[],"subpath":""}]}]}]},"dependencyType":"DIRECT","origin":"deps.dev","collector":"deps.dev"},{"id":"dependencies:b08026ef-9fab-5ea2-af3d-8d663d1f4d4c","justification":"dependency data collected via deps.dev","package":{"id":"package_types:golang","type":"golang","namespaces":[{"id":"package_namespaces:golangguac-split-@@google.golang.org","namespace":"google.golang.org","names":[{"id":"package_names:c1c08a0f-8baa-539c-91ad-f5e143249f4b","name":"genproto","versions":[{"id":"package_versions:bb1b4307-9171-5960-8539-859ef923ade0","purl":"pkg:golang/google.golang.org/genproto@v0.0.0-20210924002016-3dee208752a0","version":"v0.0.0-20210924002016-3dee208752a0","qualifiers":[],"subpath":""}]}]}]},"dependencyPackage":{"id":"package_types:golang","type":"golang","namespaces":[{"id":"package_namespaces:golangguac-split-@@google.golang.org","namespace":"google.golang.org","names":[{"id":"package_names:4833fe40-e306-5891-a53c-dda7e8f6d5fc","name":"protobuf","versions":[{"id":"package_versions:be59d0a9-9c01-5106-82f2-216581252279","purl":"pkg:golang/google.golang.org/protobuf@v1.27.1","version":"v1.27.1","qualifiers":[],"subpath":""}]}]}]},"dependencyType":"DIRECT","origin":"deps.dev","collector":"deps.dev"},{"id":"dependencies:b664a150-9861-5f5a-9be9-2deb292d1a51","justification":"dependency data collected via deps.dev","package":{"id":"package_types:golang","type":"golang","namespaces":[{"id":"package_namespaces:golangguac-split-@@google.golang.org","namespace":"google.golang.org","names":[{"id":"package_names:2dc79dd0-c1ee-528a-a1a8-7c34d7d70cf4","name":"grpc","versions":[{"id":"package_versions:3532d212-49c1-5312-81e0-934288dbff6f","purl":"pkg:golang/google.golang.org/grpc@v1.40.0","version":"v1.40.0","qualifiers":[],"subpath":""}]}]}]},"dependencyPackage":{"id":"package_types:golang","type":"golang","namespaces":[{"id":"package_namespaces:golangguac-split-@@github.com/golang","namespace":"github.com/golang","names":[{"id":"package_names:320a482a-3ad7-5a14-ad48-9304da558d41","name":"protobuf","versions":[{"id":"package_versions:59ba7431-d04d-5b33-b4be-ef0b31a54b94","purl":"pkg:golang/github.com/golang/protobuf@v1.5.2","version":"v1.5.2","qualifiers":[],"subpath":""}]}]}]},"dependencyType":"DIRECT","origin":"deps.dev","collector":"deps.dev"},{"id":"dependencies:4d04e44b-0ed6-5e93-891d-89ab13b09b69","justification":"dependency data collected via deps.dev","package":{"id":"package_types:golang","type":"golang","namespaces":[{"id":"package_namespaces:golangguac-split-@@google.golang.org","namespace":"google.golang.org","names":[{"id":"package_names:2dc79dd0-c1ee-528a-a1a8-7c34d7d70cf4","name":"grpc","versions":[{"id":"package_versions:3532d212-49c1-5312-81e0-934288dbff6f","purl":"pkg:golang/google.golang.org/grpc@v1.40.0","version":"v1.40.0","qualifiers":[],"subpath":""}]}]}]},"dependencyPackage":{"id":"package_types:golang","type":"golang","namespaces":[{"id":"package_namespaces:golangguac-split-@@github.com/google","namespace":"github.com/google","names":[{"id":"package_names:238c18ee-09d5-56bf-bc39-78997eb030f3","name":"go-cmp","versions":[{"id":"package_versions:79827ed9-63b5-5388-a107-aa05bedab549","purl":"pkg:golang/github.com/google/go-cmp@v0.5.6","version":"v0.5.6","qualifiers":[],"subpath":""}]}]}]},"dependencyType":"DIRECT","origin":"deps.dev","collector":"deps.dev"},{"id":"dependencies:bff46688-b5db-5ff4-8b35-21002ecde5ae","justification":"dependency data collected via deps.dev","package":{"id":"package_types:golang","type":"golang","namespaces":[{"id":"package_namespaces:golangguac-split-@@google.golang.org","namespace":"google.golang.org","names":[{"id":"package_names:2dc79dd0-c1ee-528a-a1a8-7c34d7d70cf4","name":"grpc","versions":[{"id":"package_versions:3532d212-49c1-5312-81e0-934288dbff6f","purl":"pkg:golang/google.golang.org/grpc@v1.40.0","version":"v1.40.0","qualifiers":[],"subpath":""}]}]}]},"dependencyPackage":{"id":"package_types:golang","type":"golang","namespaces":[{"id":"package_namespaces:golangguac-split-@@golang.org/x","namespace":"golang.org/x","names":[{"id":"package_names:10660366-cd81-5fa5-9ed3-5750e84e996e","name":"net","versions":[{"id":"package_versions:b0d4fdab-a6ad-5edc-8442-d8785917bcdd","purl":"pkg:golang/golang.org/x/net@v0.0.0-20210503060351-7fd8e65b6420","version":"v0.0.0-20210503060351-7fd8e65b6420","qualifiers":[],"subpath":""}]}]}]},"dependencyType":"DIRECT","origin":"deps.dev","collector":"deps.dev"},{"id":"dependencies:6cbd6c7d-9058-5857-9520-6ab1a2bf5885","justification":"dependency data collected via deps.dev","package":{"id":"package_types:golang","type":"golang","namespaces":[{"id":"package_namespaces:golangguac-split-@@google.golang.org","namespace":"google.golang.org","names":[{"id":"package_names:2dc79dd0-c1ee-528a-a1a8-7c34d7d70cf4","name":"grpc","versions":[{"id":"package_versions:3532d212-49c1-5312-81e0-934288dbff6f","purl":"pkg:golang/google.golang.org/grpc@v1.40.0","version":"v1.40.0","qualifiers":[],"subpath":""}]}]}]},"dependencyPackage":{"id":"package_types:golang","type":"golang","namespaces":[{"id":"package_namespaces:golangguac-split-@@golang.org/x","namespace":"golang.org/x","names":[{"id":"package_names:1c7c772b-8d57-5337-a23e-5180e6144a9a","name":"oauth2","versions":[{"id":"package_versions:1e573995-657f-55f1-86e8-cbd0c69cd52c","purl":"pkg:golang/golang.org/x/oauth2@v0.0.0-20210819190943-2bc19b11175f","version":"v0.0.0-20210819190943-2bc19b11175f","qualifiers":[],"subpath":""}]}]}]},"dependencyType":"DIRECT","origin":"deps.dev","collector":"deps.dev"},{"id":"dependencies:03bdf6be-e905-5385-9810-3a6c0da615a7","justification":"dependency data collected via deps.dev","package":{"id":"package_types:golang","type":"golang","namespaces":[{"id":"package_namespaces:golangguac-split-@@google.golang.org","namespace":"google.golang.org","names":[{"id":"package_names:2dc79dd0-c1ee-528a-a1a8-7c34d7d70cf4","name":"grpc","versions":[{"id":"package_versions:3532d212-49c1-5312-81e0-934288dbff6f","purl":"pkg:golang/google.golang.org/grpc@v1.40.0","version":"v1.40.0","qualifiers":[],"subpath":""}]}]}]},"dependencyPackage":{"id":"package_types:golang","type":"golang","namespaces":[{"id":"package_namespaces:golangguac-split-@@golang.org/x","namespace":"golang.org/x","names":[{"id":"package_names:6c0a9691-7a6f-5176-a395-cab080877631","name":"sys","versions":[{"id":"package_versions:23e077f5-164f-5824-94be-59a13126e7d8","purl":"pkg:golang/golang.org/x/sys@v0.0.0-20210908233432-aa78b53d3365","version":"v0.0.0-20210908233432-aa78b53d3365","qualifiers":[],"subpath":""}]}]}]},"dependencyType":"DIRECT","origin":"deps.dev","collector":"deps.dev"},{"id":"dependencies:42026c20-3654-5556-aa87-c014b393e840","justification":"dependency data collected via deps.dev","package":{"id":"package_types:golang","type":"golang","namespaces":[{"id":"package_namespaces:golangguac-split-@@google.golang.org","namespace":"google.golang.org","names":[{"id":"package_names:2dc79dd0-c1ee-528a-a1a8-7c34d7d70cf4","name":"grpc","versions":[{"id":"package_versions:3532d212-49c1-5312-81e0-934288dbff6f","purl":"pkg:golang/google.golang.org/grpc@v1.40.0","version":"v1.40.0","qualifiers":[],"subpath":""}]}]}]},"dependencyPackage":{"id":"package_types:golang","type":"golang","namespaces":[{"id":"package_namespaces:golangguac-split-@@google.golang.org","namespace":"google.golang.org","names":[{"id":"package_names:c1c08a0f-8baa-539c-91ad-f5e143249f4b","name":"genproto","versions":[{"id":"package_versions:bb1b4307-9171-5960-8539-859ef923ade0","purl":"pkg:golang/google.golang.org/genproto@v0.0.0-20210924002016-3dee208752a0","version":"v0.0.0-20210924002016-3dee208752a0","qualifiers":[],"subpath":""}]}]}]},"dependencyType":"DIRECT","origin":"deps.dev","collector":"deps.dev"},{"id":"dependencies:7757b961-67f8-52cb-8464-d86e8fb90a3a","justification":"dependency data collected via deps.dev","package":{"id":"package_types:golang","type":"golang","namespaces":[{"id":"package_namespaces:golangguac-split-@@google.golang.org","namespace":"google.golang.org","names":[{"id":"package_names:2dc79dd0-c1ee-528a-a1a8-7c34d7d70cf4","name":"grpc","versions":[{"id":"package_versions:3532d212-49c1-5312-81e0-934288dbff6f","purl":"pkg:golang/google.golang.org/grpc@v1.40.0","version":"v1.40.0","qualifiers":[],"subpath":""}]}]}]},"dependencyPackage":{"id":"package_types:golang","type":"golang","namespaces":[{"id":"package_namespaces:golangguac-split-@@google.golang.org","namespace":"google.golang.org","names":[{"id":"package_names:4833fe40-e306-5891-a53c-dda7e8f6d5fc","name":"protobuf","versions":[{"id":"package_versions:be59d0a9-9c01-5106-82f2-216581252279","purl":"pkg:golang/google.golang.org/protobuf@v1.27.1","version":"v1.27.1","qualifiers":[],"subpath":""}]}]}]},"dependencyType":"DIRECT","origin":"deps.dev","collector":"deps.dev"},{"id":"dependencies:7237d5cd-f5dc-5fb1-b4cb-810110f53d3f","justification":"dependency data collected via deps.dev","package":{"id":"package_types:golang","type":"golang","namespaces":[{"id":"package_namespaces:golangguac-split-@@google.golang.org","namespace":"google.golang.org","names":[{"id":"package_names:4833fe40-e306-5891-a53c-dda7e8f6d5fc","name":"protobuf","versions":[{"id":"package_versions:be59d0a9-9c01-5106-82f2-216581252279","purl":"pkg:golang/google.golang.org/protobuf@v1.27.1","version":"v1.27.1","qualifiers":[],"subpath":""}]}]}]},"dependencyPackage":{"id":"package_types:golang","type":"golang","namespaces":[{"id":"package_namespaces:golangguac-split-@@github.com/google","namespace":"github.com/google","names":[{"id":"package_names:238c18ee-09d5-56bf-bc39-78997eb030f3","name":"go-cmp","versions":[{"id":"package_versions:79827ed9-63b5-5388-a107-aa05bedab549","purl":"pkg:golang/github.com/google/go-cmp@v0.5.6","version":"v0.5.6","qualifiers":[],"subpath":""}]}]}]},"dependencyType":"DIRECT","origin":"deps.dev","collector":"deps.dev"}],"includedOccurrences":[]}